gpiocontrol/__init__.py
gpiocontrol/get.py
gpiocontrol/set.py
gpiocontrol/state.py
gpiocontrol-1.1.dist-info/METADATA
gpiocontrol-1.1.dist-info/WHEEL
gpiocontrol-1.1.dist-info/top_level.txt
gpiocontrol-1.1.dist-info/RECORD
