Metadata-Version: 2.1
Name: gpiocontrol
Version: 1.1
Summary: Simple wrapper for bash commands to control GPIO.
Author: s17kf
